LICENSE
MANIFEST.in
README.md
setup.py
bin/kata
src/kata/__init__.py
src/kata/defaults.py
src/kata.egg-info/PKG-INFO
src/kata.egg-info/SOURCES.txt
src/kata.egg-info/dependency_links.txt
src/kata.egg-info/requires.txt
src/kata.egg-info/top_level.txt
src/kata/data/__init__.py
src/kata/data/repos.py
src/kata/data/io/__init__.py
src/kata/data/io/file.py
src/kata/data/io/network.py
src/kata/domain/__init__.py
src/kata/domain/exceptions.py
src/kata/domain/grepo.py
src/kata/domain/models.py
src/kata/domain/services.py
src/kata/presentation/__init__.py
src/kata/presentation/cli.py