Metadata-Version: 1.1
Name: kata
Version: 1.1.0
Summary: Kata made easy: A TDD setup in the language of your choice in a single command
Home-page: https://floriankempenich.github.data/kata
Author: Florian Kempenich
Author-email: Flori@nKempenich.com
License: MIT
Keywords: test tdd kata clean-code softwarecraft
Platform: UNKNOWN
Classifier: Environment :: Console
Classifier: Intended Audience :: Developers
Classifier: License :: OSI Approved :: MIT License
Classifier: Topic :: Utilities
Classifier: Topic :: Software Development :: Testing
